nicegui_toolkit/__init__.py
nicegui_toolkit/layout_tool/__init__.py
nicegui_toolkit/layout_tool/consts.py
nicegui_toolkit/layout_tool/element_tree.py
nicegui_toolkit/layout_tool/events.py
nicegui_toolkit/layout_tool/language.py
nicegui_toolkit/layout_tool/record_tracker.py
nicegui_toolkit/layout_tool/services/caller_service.py
nicegui_toolkit/layout_tool/services/intercept_service.py
nicegui_toolkit/layout_tool/services/source_code_service.py
nicegui_toolkit/layout_tool/tailwindcss/__init__.py
nicegui_toolkit/layout_tool/tailwindcss/query.py
nicegui_toolkit/layout_tool/tailwindcss/tailwindcss.db
nicegui_toolkit/layout_tool/track_ball/libs/trackBall.css
nicegui_toolkit/layout_tool/track_ball/trackBall.js
nicegui_toolkit/layout_tool/track_ball/trackBall.py
nicegui_toolkit/layout_tool/types.py
nicegui_toolkit/systems/caller_system.py
nicegui_toolkit/systems/fastapi_system.py
nicegui_toolkit/systems/file_system.py
nicegui_toolkit/systems/frame_system.py
nicegui_toolkit/systems/object_system.py
nicegui_toolkit/version.py
niceguitoolkit-0.3.0.dist-info/LICENSE
niceguitoolkit-0.3.0.dist-info/METADATA
niceguitoolkit-0.3.0.dist-info/WHEEL
niceguitoolkit-0.3.0.dist-info/RECORD
