Metadata-Version: 2.1
Name: niceguiToolkit
Version: 0.3.0
Summary: toolkit for nicegui
Home-page: https://github.com/CrystalWindSnake/nicegui-toolkit
License: MIT
Keywords: nicegui,webui
Author: CrystalWindSnake
Author-email: 568166495@qq.com
Requires-Python: >=3.8,<4.0
Classifier: License :: OSI Approved :: MIT License
Classifier: Programming Language :: Python :: 3
Classifier: Programming Language :: Python :: 3.8
Classifier: Programming Language :: Python :: 3.9
Classifier: Programming Language :: Python :: 3.10
Classifier: Programming Language :: Python :: 3.11
Classifier: Programming Language :: Python :: 3.12
Requires-Dist: asttokens (>=2.4.1,<3.0.0)
Requires-Dist: executing (>=2.1.0,<3.0.0)
Requires-Dist: nicegui (>=2.0.0,<3.0.0)
Project-URL: Repository, https://github.com/CrystalWindSnake/nicegui-toolkit
